pipecat_ai_tail-0.0.2.dist-info/licenses/LICENSE
pipecat_tail/__init__.py
pipecat_tail/__version__.py
pipecat_tail/app.py
pipecat_tail/cli.py
pipecat_tail/observer.py
pipecat_tail/py.typed
pipecat_tail/rtvi.py
pipecat_tail/runner.py
pipecat_tail/tail.tcss
pipecat_tail/widgets/__init__.py
pipecat_tail/widgets/audio_level.py
pipecat_tail/widgets/conversation.py
pipecat_tail/widgets/llm_service_info.py
pipecat_tail/widgets/service_metrics.py
pipecat_tail/widgets/streaming_log.py
pipecat_tail/widgets/system_info.py
pipecat_tail/widgets/system_logs.py
pipecat_tail/widgets/system_status.py
pipecat_tail/widgets/tts_service_info.py
pipecat_ai_tail-0.0.2.dist-info/METADATA
pipecat_ai_tail-0.0.2.dist-info/WHEEL
pipecat_ai_tail-0.0.2.dist-info/entry_points.txt
pipecat_ai_tail-0.0.2.dist-info/top_level.txt
pipecat_ai_tail-0.0.2.dist-info/RECORD
