Metadata-Version: 2.4
Name: pipecat-ai-tail
Version: 0.0.2
Summary: A pipeline runner for Pipecat
License-Expression: BSD-2-Clause
Project-URL: Source, https://github.com/pipecat-ai/tail
Project-URL: Website, https://pipecat.ai
Keywords: pipecat,ai
Classifier: Development Status :: 5 - Production/Stable
Classifier: Intended Audience :: Developers
Classifier: Topic :: Communications :: Conferencing
Classifier: Topic :: Multimedia :: Sound/Audio
Classifier: Topic :: Multimedia :: Video
Classifier: Topic :: Scientific/Engineering :: Artificial Intelligence
Requires-Python: >=3.10
License-File: LICENSE
Requires-Dist: pipecat-ai>=0.0.87
Requires-Dist: textual<7,>=6.0.0
Requires-Dist: textual-plotext<2,>=1.0.0
Requires-Dist: typer<1,>=0.20.0
Requires-Dist: websockets<15.0,>=13.1
Dynamic: license-file
